pypideptree/__init__.py
pypideptree/pypi.py
pypideptree-0.1.0.dist-info/METADATA
pypideptree-0.1.0.dist-info/WHEEL
pypideptree-0.1.0.dist-info/entry_points.txt
pypideptree-0.1.0.dist-info/top_level.txt
pypideptree-0.1.0.dist-info/RECORD
