Metadata-Version: 2.1
Name: pypideptree
Version: 0.1.0
Summary: simple crontab implemented on thread executor pool
Home-page: https://github.com/weaming/pypideptree
Author: weaming
Author-email: garden.yuen@gmail.com
License: UNKNOWN
Project-URL: Source, https://github.com/weaming/pypideptree
Project-URL: Bug Reports, https://github.com/weaming/pypideptree
Keywords: tools,developer
Platform: UNKNOWN
